zymptest/__init__.py
zymptest/zymtest.py
zymptest-0.2.2.dist-info/METADATA
zymptest-0.2.2.dist-info/RECORD
zymptest-0.2.2.dist-info/WHEEL
zymptest-0.2.2.dist-info/top_level.txt
